geersd.py
geersd-0.1.2.dist-info/LICENSE
geersd-0.1.2.dist-info/METADATA
geersd-0.1.2.dist-info/WHEEL
geersd-0.1.2.dist-info/top_level.txt
geersd-0.1.2.dist-info/RECORD
